envrpt/__init__.py
envrpt/__main__.py
envrpt/cli.py
envrpt/core.py
envrpt/vulnerabilities.py
envrpt/_vendor/__init__.py
envrpt/_vendor/ashes/LICENSE
envrpt/_vendor/ashes/__init__.py
envrpt/report/__init__.py
envrpt/report/basic.py
envrpt/report/console.py
envrpt/report/html.py
envrpt/report/json.py
envrpt/report/markdown.py
envrpt-0.1.0.dist-info/LICENSE.rst
envrpt-0.1.0.dist-info/METADATA
envrpt-0.1.0.dist-info/WHEEL
envrpt-0.1.0.dist-info/entry_points.txt
envrpt-0.1.0.dist-info/top_level.txt
envrpt-0.1.0.dist-info/zip-safe
envrpt-0.1.0.dist-info/RECORD
