Metadata-Version: 2.1
Name: envrpt
Version: 0.1.0
Summary: Analyzes the packages installed in a Python environment
Home-page: https://github.com/jayclassless/envrpt
Author: Jason Simeone
Author-email: jay@classless.net
License: MIT
Keywords: virtual environment package dependency analysis
Platform: UNKNOWN
Classifier: Environment :: Console
Classifier: Intended Audience :: Developers
Classifier: License :: OSI Approved :: MIT License
Classifier: Programming Language :: Python
Classifier: Programming Language :: Python :: 3.5
Classifier: Programming Language :: Python :: 3.6
Classifier: Programming Language :: Python :: 3.7
Classifier: Programming Language :: Python :: 3.8
Classifier: Programming Language :: Python :: Implementation :: CPython
Classifier: Programming Language :: Python :: Implementation :: PyPy
Classifier: Topic :: Software Development
Classifier: Development Status :: 4 - Beta
Requires-Dist: pip (>=10)
